CHANGES.txt
README.txt
VERSION.txt
setup.py
koansys/__init__.py
koansys.django.authradius.egg-info/PKG-INFO
koansys.django.authradius.egg-info/SOURCES.txt
koansys.django.authradius.egg-info/dependency_links.txt
koansys.django.authradius.egg-info/namespace_packages.txt
koansys.django.authradius.egg-info/not-zip-safe
koansys.django.authradius.egg-info/requires.txt
koansys.django.authradius.egg-info/top_level.txt
koansys/django/__init__.py
koansys/django/authradius.py