Metadata-Version: 1.0
Name: koansys.django.authradius
Version: 1.0.2
Summary: Django can authenticate against a RADIUS server
Home-page: http://koansys-django-authradius.googlecode.com/
Author: Chris Shenton
Author-email: chris@koansys.com
License: BSD
Keywords: authentication
Platform: UNKNOWN
Classifier: Programming Language :: Python
Classifier: Development Status :: 5 - Production/Stable
Classifier: Framework :: Django
Classifier: Intended Audience :: Developers
Classifier: Operating System :: OS Independent
Classifier: License :: OSI Approved :: BSD License
